[{"name": "R Sakthi Priya", "ragamId": "UUTCCZ", "college": "Mar Baselios College of Engineering and Technology", "events": [{"name": "Crime Scene Investigation (CSI)", "category": "General", "status": "Knocked Out", "hasCertificate": false}, {"name": "Fresco", "category": "General", "status": "Knocked Out", "hasCertificate": false}, {"name": "Mehendi", "category": "Fine Arts", "status": "Knocked Out", "hasCertificate": false}, {"name": "Treasure Hunt", "category": "General", "status": "Knocked Out", "hasCertificate": false}]}]